robobopy_audiostream/Exceptions.py
robobopy_audiostream/RoboboAudio.py
robobopy_audiostream/__init__.py
robobopy_audiostream/audiosocket.py
robobopy_audiostream-1.1.0.dist-info/LICENSE
robobopy_audiostream-1.1.0.dist-info/METADATA
robobopy_audiostream-1.1.0.dist-info/WHEEL
robobopy_audiostream-1.1.0.dist-info/top_level.txt
robobopy_audiostream-1.1.0.dist-info/RECORD
